smilesfeature/__init__.py
smilesfeature/constant.py
smilesfeature/core.py
smilesfeature/utils.py
smilesfeature/data/__init__.py
smilesfeature/data/model_300dim.pkl
smilesfeature/processor/__init__.py
smilesfeature/processor/mol2vec_processor.py
smilesfeature/processor/smiles_processor.py
smilesfeature-0.1.15.dist-info/LICENSE
smilesfeature-0.1.15.dist-info/METADATA
smilesfeature-0.1.15.dist-info/WHEEL
smilesfeature-0.1.15.dist-info/entry_points.txt
smilesfeature-0.1.15.dist-info/top_level.txt
smilesfeature-0.1.15.dist-info/RECORD
